{
  "frontend": [
    "next.js",
    "react",
    "svelte",
    "html",
    "css",
    "tailwindcss",
    "styled-components",
    "materialui",
    "bootstrap"
  ],
  "backend": ["next.js", "express", "sveltekit", "nodejs"],
  "languages": ["javascript", "typescript"],
  "databases": ["mongodb", "postgresql", "mongoose", "prisma"],
  "softskills": [
    "pair programming",
    "problem solving",
    "critical thinking",
    "self-learning",
    "teamwork",
    "communication"
  ],
  "tools": ["git", "github", "vscode", "docker", "npm", "bun"],
  "testing": ["jest", "vitest", "cypress"],
  "design": ["photoshop", "illustrator", "figma", "procreate"],
  "cloudservices": ["vercel", "netlify", "aws"],
  "project-management": ["agile", "scrum", "kanban", "jira"],
  "mobileDevelopment": ["react native"]
}
